code/week4_p4.v
module mux4(input wire [0:3] i, input wire j0, j1, output wire o);
    wire [0:1] s;
    assign s = j1 ? {j0, 1'b1} : {j0, 1'b0};
    
    assign o = (s == 2'b00) ? i[0] :
              (s == 2'b01) ? i[1] :
              (s == 2'b10) ? i[2] :
			     i[3];
                  
endmodule

code/week4_p4_tb.v
module TB;
    reg [0:3]ii;
    reg s0;reg s1;
    wire yy;
    mux4 newMUX(.i(ii), .j0(s0),.j1(s1),.o(yy));
    initial begin
        ii = 4'b0000;s0=1'b0;s1=1'b0;
        #5      ii = 4'b1000;s0=1'b0;s1=1'b0;
        #5      ii = 4'b0000;s0=1'b0;s1=1'b1;
        #5      ii = 4'b0100;s0=1'b0;s1=1'b1;
        #5      ii = 4'b0000;s0=1'b1;s1=1'b0;
        #5      ii = 4'b0010;s0=1'b1;s1=1'b0;
        #5      ii = 4'b0000;s0=1'b1;s1=1'b1;
        #5      ii = 4'b0001;s0=1'b1;s1=1'b1;
    end
    initial begin
        $monitor("Time = %0t: ii = %b, s0 = %b, s1 = %b, yy = %b", $time, ii, s0, s1, yy);
    end
    initial begin
        $dumpfile("week4_p4.vcd");
        $dumpvars(0, TB);
    end
endmodule

code/week4_p4.vcd
$date
	Tue Sep 10 09:43:42 2024
$end
$version
	Icarus Verilog
$end
$timescale
	1s
$end
$scope module TB $end
$var wire 1 ! yy $end
$var reg 4 " ii [0:3] $end
$var reg 1 # s0 $end
$var reg 1 $ s1 $end
$scope module newMUX $end
$var wire 4 % i [0:3] $end
$var wire 1 & j0 $end
$var wire 1 ' j1 $end
$var wire 1 ! o $end
$var wire 2 ( s [0:1] $end
$upscope $end
$upscope $end
$enddefinitions $end
#0
$dumpvars
b0 (
0'
0&
b0 %
0$
0#
b0 "
0!
$end
#5
1!
b1000 "
b1000 %
#10
0!
b1 (
1$
1'
b0 "
b0 %
#15
1!
b100 "
b100 %
#20
0!
b10 (
0$
0'
1#
1&
b0 "
b0 %
#25
1!
b10 "
b10 %
#30
0!
b11 (
1$
1'
b0 "
b0 %
#35
1!
b1 "
b1 %
