code/week3_p3.v
module fulladder (
    input wire a,b,cin,
    output wire sum,cout
);

assign sum = a ^ b ^ cin;      
assign cout = (a & b) | (cin & (a ^ b));

endmodule

module fulladdR ( 
    input wire [3:0] a, b, 
    input wire cin, 
    output wire [3:0] sum,
    output wire cout 
);

wire [2:0] c; 

fulladder u0 (a[0], b[0], cin, sum[0], cout0); 

fulladder u1 (a[1], b[1], cout0, sum[1], cout1); 

fulladder u2 (a[2], b[2], cout1, sum[2], cout2); 

fulladder u3 (a[3], b[3], cout2, sum[3], cout); 

endmodule

code/rcatb.v
`timescale 1 ns / 100 ps
`define TESTVECS 10

module tb; 
    reg clk, reset; 
    reg [3:0] i0, i1; 
    reg cin; 
    wire [3:0] o; 
    wire cout; 
    reg [8:0] test_vecs[0:(`TESTVECS-1)]; 
    integer i; 

    // Instantiate the fulladdR module
    fulladdR u0 ( 
        .a(i0), .b(i1), .cin(cin), 
        .sum(o), .cout(cout) 
    ); 

    initial begin 
        $dumpfile("rca_test.vcd"); 
        $dumpvars(0, tb); 
    end 

    initial begin 
        reset = 1'b1; 
        #12.5 reset = 1'b0; 
    end 

    initial clk = 1'b0; 
    always #5 clk = ~clk; 

    initial begin 
        test_vecs[0] = 9'b000000000; 
        test_vecs[1] = 9'b000000001;
        test_vecs[2] = 9'b000100010; 
        test_vecs[3] = 9'b000100011; 
        test_vecs[4] = 9'b001000100; 
        test_vecs[5] = 9'b101010110; 
        test_vecs[6] = 9'b101010111; 
        test_vecs[7] = 9'b110011010; 
        test_vecs[8] = 9'b111111100; 
        test_vecs[9] = 9'b111111101; 
    end 

    initial begin 
        #6 
        for (i = 0; i < `TESTVECS; i = i + 1) begin 
            #10;
            {i0, i1, cin} = test_vecs[i]; 
        end 
        #100 $finish;
    end 

    always @(i0 or i1 or cin)
        $monitor( "At time = %t, i0=%b, i1=%b, cin=%b, Sum=%b, Carry=%b", $time, i0, i1, cin, o, cout );

endmodule

code/week3_p3.vcd
$date
	Thu Aug 29 12:57:06 2024
$end
$version
	Icarus Verilog
$end
$timescale
	1s
$end
$scope module tb $end
$var wire 1 ! cout $end
$var wire 4 " o [3:0] $end
$var reg 1 # cin $end
$var reg 1 $ clk $end
$var integer 32 % i [31:0] $end
$var reg 4 & i0 [3:0] $end
$var reg 4 ' i1 [3:0] $end
$var reg 1 ( reset $end
$scope module u0 $end
$var wire 4 ) a [3:0] $end
$var wire 4 * b [3:0] $end
$var wire 1 + cin $end
$var wire 1 ! cout $end
$var wire 1 , cout0 $end
$var wire 1 - cout1 $end
$var wire 1 . cout2 $end
$var wire 4 / sum [3:0] $end
$scope module u0 $end
$var wire 1 0 a $end
$var wire 1 1 b $end
$var wire 1 + cin $end
$var wire 1 , cout $end
$var wire 1 2 sum $end
$upscope $end
$scope module u1 $end
$var wire 1 3 a $end
$var wire 1 4 b $end
$var wire 1 , cin $end
$var wire 1 - cout $end
$var wire 1 5 sum $end
$upscope $end
$scope module u2 $end
$var wire 1 6 a $end
$var wire 1 7 b $end
$var wire 1 - cin $end
$var wire 1 . cout $end
$var wire 1 8 sum $end
$upscope $end
$scope module u3 $end
$var wire 1 9 a $end
$var wire 1 : b $end
$var wire 1 . cin $end
$var wire 1 ! cout $end
$var wire 1 ; sum $end
$upscope $end
$upscope $end
$upscope $end
$enddefinitions $end
#0
$dumpvars
0;
0:
09
08
07
06
05
04
03
02
01
00
b0 /
0.
0-
0,
0+
b0 *
b0 )
1(
b0 '
b0 &
b0 %
0$
0#
b0 "
0!
$end
#5
1$
#10
0$
#13
0(
#15
1$
#16
b1 %
#20
0$
#25
1$
#26
12
b1 "
b1 /
b10 %
1#
1+
#30
0$
#35
1$
#36
15
1,
10
11
02
b10 "
b10 /
b11 %
b1 &
b1 )
b1 '
b1 *
0#
0+
#40
0$
#45
1$
#46
12
b11 "
b11 /
b100 %
1#
1+
#50
0$
#55
1$
#56
05
18
0,
1-
00
13
01
14
02
b100 "
b100 /
b101 %
b10 &
b10 )
b10 '
b10 *
0#
0+
#60
0$
#65
1$
#66
12
b101 "
b101 /
1!
19
11
1:
b110 %
b1010 &
b1010 )
b1011 '
b1011 *
#70
0$
#75
1$
#76
15
1,
02
b110 "
b110 /
b111 %
1#
1+
#80
0$
#85
1$
#86
08
1;
0-
1.
05
0,
03
16
04
17
12
b1001 "
b1001 /
b1000 %
b1100 &
b1100 )
b1101 '
b1101 *
0#
0+
#90
0$
#95
1$
#96
18
b1101 "
b1101 /
1-
10
13
01
14
b1001 %
b1111 &
b1111 )
b1110 '
b1110 *
#100
0$
#105
1$
#106
15
1,
02
b1110 "
b1110 /
b1010 %
1#
1+
